Workbook

Sheet Crop_Cultivation
A1: Cultivation_ID | B1: Crop | C1: Area_Acres | D1: Planting_Month | E1: Year | F1: Cultivation_Status
A2: C001 | B2: Lady's Finger | C2: 1 | D2: January | E2: 2026 | F2: Actual
A3: C002 | B3: Maize | C3: 2 | D3: January | E3: 2026 | F3: Actual
A4: C003 | B4: Cotton | C4: 1 | D4: February | E4: 2026 | F4: Actual
A5: C004 | B5: Lady's Finger | C5: 1 | D5: September | E5: 2026 | F5: Planned
A6: C005 | B6: Cotton | C6: 1 | D6: September | E6: 2026 | F6: Planned
A7: C006 | B7: Maize | C7: 2 | D7: September | E7: 2026 | F7: Planned

Sheet Expenses
A1: Expense_ID | B1: Cultivation_ID | C1: Category | D1: Type | E1: Amount_Per_Acre | F1: Area | G1: Total | H1: Status | I1: Crop | J1: Planting_Month | K1: Cultivation_Status
A2: E001 | B2: C002 | C2: Fertilizer | D2: Fertilizer | E2: 4500 | F2: 2 | G2: =E2*F2 -> 9000 | H2: Approximate | I2: =_xlfn.XLOOKUP(B2,Crop_Cultivation!A:A,Crop_Cultivation!B:B) -> Maize | J2: =_xlfn.XLOOKUP(B2,Crop_Cultivation!A:A,Crop_Cultivation!D:D) -> January | K2: =_xlfn.XLOOKUP(B2,Crop_Cultivation!A:A,Crop_Cultivation!F:F) -> Actual
A3: E002 | B3: C002 | C3: Pesticide | D3: Pesticide | E3: 1000 | F3: 2 | G3: =E3*F3 -> 2000 | H3: Approximate | I3: =_xlfn.XLOOKUP(B3,Crop_Cultivation!A:A,Crop_Cultivation!B:B) -> Maize | J3: =_xlfn.XLOOKUP(B3,Crop_Cultivation!A:A,Crop_Cultivation!D:D) -> January | K3: =_xlfn.XLOOKUP(B3,Crop_Cultivation!A:A,Crop_Cultivation!F:F) -> Actual
A4: E003 | B4: C002 | C4: Labour | D4: Land filling | E4: 2000 | F4: 2 | G4: =E4*F4 -> 4000 | H4: Approximate | I4: =_xlfn.XLOOKUP(B4,Crop_Cultivation!A:A,Crop_Cultivation!B:B) -> Maize | J4: =_xlfn.XLOOKUP(B4,Crop_Cultivation!A:A,Crop_Cultivation!D:D) -> January | K4: =_xlfn.XLOOKUP(B4,Crop_Cultivation!A:A,Crop_Cultivation!F:F) -> Actual
A5: E004 | B5: C002 | C5: Labour | D5: Manual tilling | E5: 2000 | F5: 2 | G5: =E5*F5 -> 4000 | H5: Approximate | I5: =_xlfn.XLOOKUP(B5,Crop_Cultivation!A:A,Crop_Cultivation!B:B) -> Maize | J5: =_xlfn.XLOOKUP(B5,Crop_Cultivation!A:A,Crop_Cultivation!D:D) -> January | K5: =_xlfn.XLOOKUP(B5,Crop_Cultivation!A:A,Crop_Cultivation!F:F) -> Actual
A6: E005 | B6: C002 | C6: Labour | D6: Planting | E6: 1000 | F6: 2 | G6: =E6*F6 -> 2000 | H6: Approximate | I6: =_xlfn.XLOOKUP(B6,Crop_Cultivation!A:A,Crop_Cultivation!B:B) -> Maize | J6: =_xlfn.XLOOKUP(B6,Crop_Cultivation!A:A,Crop_Cultivation!D:D) -> January | K6: =_xlfn.XLOOKUP(B6,Crop_Cultivation!A:A,Crop_Cultivation!F:F) -> Actual
A7: E006 | B7: C002 | C7: Labour | D7: Weeding | E7: 3000 | F7: 2 | G7: =E7*F7 -> 6000 | H7: Approximate | I7: =_xlfn.XLOOKUP(B7,Crop_Cultivation!A:A,Crop_Cultivation!B:B) -> Maize | J7: =_xlfn.XLOOKUP(B7,Crop_Cultivation!A:A,Crop_Cultivation!D:D) -> January | K7: =_xlfn.XLOOKUP(B7,Crop_Cultivation!A:A,Crop_Cultivation!F:F) -> Actual
A8: E007 | B8: C002 | C8: Labour | D8: Harvesting | E8: 4000 | F8: 2 | G8: =E8*F8 -> 8000 | H8: Approximate | I8: =_xlfn.XLOOKUP(B8,Crop_Cultivation!A:A,Crop_Cultivation!B:B) -> Maize | J8: =_xlfn.XLOOKUP(B8,Crop_Cultivation!A:A,Crop_Cultivation!D:D) -> January | K8: =_xlfn.XLOOKUP(B8,Crop_Cultivation!A:A,Crop_Cultivation!F:F) -> Actual
A9: E008 | B9: C002 | C9: Labour | D9: Threshing | E9: 2000 | F9: 2 | G9: =E9*F9 -> 4000 | H9: Approximate | I9: =_xlfn.XLOOKUP(B9,Crop_Cultivation!A:A,Crop_Cultivation!B:B) -> Maize | J9: =_xlfn.XLOOKUP(B9,Crop_Cultivation!A:A,Crop_Cultivation!D:D) -> January | K9: =_xlfn.XLOOKUP(B9,Crop_Cultivation!A:A,Crop_Cultivation!F:F) -> Actual
A10: E009 | B10: C002 | C10: Irrigation | D10: Irrigation | E10: 5000 | F10: 2 | G10: =E10*F10 -> 10000 | H10: Approximate | I10: =_xlfn.XLOOKUP(B10,Crop_Cultivation!A:A,Crop_Cultivation!B:B) -> Maize | J10: =_xlfn.XLOOKUP(B10,Crop_Cultivation!A:A,Crop_Cultivation!D:D) -> January | K10: =_xlfn.XLOOKUP(B10,Crop_Cultivation!A:A,Crop_Cultivation!F:F) -> Actual
A11: E010 | B11: C002 | C11: Seed | D11: Seed | E11: 2100 | F11: 2 | G11: =E11*F11 -> 4200 | H11: Approximate | I11: =_xlfn.XLOOKUP(B11,Crop_Cultivation!A:A,Crop_Cultivation!B:B) -> Maize | J11: =_xlfn.XLOOKUP(B11,Crop_Cultivation!A:A,Crop_Cultivation!D:D) -> January | K11: =_xlfn.XLOOKUP(B11,Crop_Cultivation!A:A,Crop_Cultivation!F:F) -> Actual
A12: E011 | B12: C001 | C12: Fertilizer | D12: Fertilizer - Application 1 | E12: 1000 | F12: 1 | G12: =E12*F12 -> 1000 | H12: Approximate | I12: =_xlfn.XLOOKUP(B12,Crop_Cultivation!A:A,Crop_Cultivation!B:B) -> Lady's Finger | J12: =_xlfn.XLOOKUP(B12,Crop_Cultivation!A:A,Crop_Cultivation!D:D) -> January | K12: =_xlfn.XLOOKUP(B12,Crop_Cultivation!A:A,Crop_Cultivation!F:F) -> Actual
A13: E012 | B13: C001 | C13: Fertilizer | D13: Fertilizer - Application 2 | E13: 3000 | F13: 1 | G13: =E13*F13 -> 3000 | H13: Approximate | I13: =_xlfn.XLOOKUP(B13,Crop_Cultivation!A:A,Crop_Cultivation!B:B) -> Lady's Finger | J13: =_xlfn.XLOOKUP(B13,Crop_Cultivation!A:A,Crop_Cultivation!D:D) -> January | K13: =_xlfn.XLOOKUP(B13,Crop_Cultivation!A:A,Crop_Cultivation!F:F) -> Actual
... A66: E065 | B66: C001 | C66: Labour | D66: Harvesting | E66: 15000 | F66: 1 | G66: =E66*F66 -> 15000 | H66: Approximate | I66: =_xlfn.XLOOKUP(B66,Crop_Cultivation!A:A,Crop_Cultivation!B:B) -> Lady's Finger | J66: =_xlfn.XLOOKUP(B66,Crop_Cultivation!A:A,Crop_Cultivation!D:D) -> January | K66: =_xlfn.XLOOKUP(B66,Crop_Cultivation!A:A,Crop_Cultivation!F:F) -> Actual

Sheet Harvest
A1: Harvest_ID | B1: Cultivation_ID | C1: Crop | D1: Harvest_No | E1: Quantity_Kg | F1: Data_Status | G1: Planting_Month | H1: Cultivation_Status
A2: H001 | B2: C002 | C2: Maize | D2: 1 | E2: 5000 | F2: Approximate | G2: =_xlfn.XLOOKUP(B2,Crop_Cultivation!A:A,Crop_Cultivation!D:D) -> January | H2: =_xlfn.XLOOKUP(B2,Crop_Cultivation!A:A,Crop_Cultivation!F:F) -> Actual
A3: H002 | B3: C001 | C3: Lady's Finger | D3: 1 | E3: 390 | F3: Approximate | G3: =_xlfn.XLOOKUP(B3,Crop_Cultivation!A:A,Crop_Cultivation!D:D) -> January | H3: =_xlfn.XLOOKUP(B3,Crop_Cultivation!A:A,Crop_Cultivation!F:F) -> Actual
A4: H003 | B4: C003 | C4: Cotton | D4: 1 | E4: 1200 | F4: Approximate | G4: =_xlfn.XLOOKUP(B4,Crop_Cultivation!A:A,Crop_Cultivation!D:D) -> February | H4: =_xlfn.XLOOKUP(B4,Crop_Cultivation!A:A,Crop_Cultivation!F:F) -> Actual

Sheet Sales
A1: Sale_ID | B1: Cultivation_ID | C1: Crop | D1: Quantity_Kg | E1: Selling_Price_Per_Kg | F1: Total_Revenue | G1: Data_Status | H1: Planting_Month | I1: Cultivation_Status
A2: S001 | B2: C002 | C2: Maize | D2: 5000 | E2: 20 | F2: =D2*E2 -> 100000 | G2: Approximate | H2: =_xlfn.XLOOKUP(B2,Crop_Cultivation!A:A,Crop_Cultivation!D:D) -> January | I2: =_xlfn.XLOOKUP(B2,Crop_Cultivation!A:A,Crop_Cultivation!F:F) -> Actual
A3: S002 | B3: C001 | C3: Lady's Finger | D3: 390 | E3: 100 | F3: =D3*E3 -> 39000 | G3: Approximate | H3: =_xlfn.XLOOKUP(B3,Crop_Cultivation!A:A,Crop_Cultivation!D:D) -> January | I3: =_xlfn.XLOOKUP(B3,Crop_Cultivation!A:A,Crop_Cultivation!F:F) -> Actual
A4: S003 | B4: C003 | C4: Cotton | D4: 1200 | E4: 80 | F4: =D4*E4 -> 96000 | G4: Approximate | H4: =_xlfn.XLOOKUP(B4,Crop_Cultivation!A:A,Crop_Cultivation!D:D) -> February | I4: =_xlfn.XLOOKUP(B4,Crop_Cultivation!A:A,Crop_Cultivation!F:F) -> Actual
F5: =SUM(F2:F4) -> 235000

Sheet Summary
A1: Metric | B1: Value | D1: Crop | E1: Area_Acres | F1: Total_Cost | G1: Production_Kg | H1: Revenue | I1: Profit | J1: ROI_%
A2: Total Cultivated Area | B2: =SUM(E2:E4) -> 4 | D2: Maize | E2: =SUMIFS(Crop_Cultivation!$C:$C,Crop_Cultivation!$B:$B,D2,Crop_Cultivation!$F:$F,"Actual") -> 2 | F2: =SUMIFS(Expenses!$G:$G,Expenses!$I:$I,D2,Expenses!$H:$H,"Approximate") -> 53200 | G2: =SUMIFS(Harvest!$E:$E,Harvest!$C:$C,D2,Harvest!$F:$F,"Approximate") -> 5000 | H2: =SUMIFS(Sales!$F:$F,Sales!$C:$C,D2,Sales!$G:$G,"Approximate") -> 100000 | I2: =H2-F2 -> 46800 | J2: =IFERROR(I2/F2,0) -> 0.87969925
A3: Total Expenses | B3: =SUM(F2:F4) -> 153700 | D3: Cotton | E3: =SUMIFS(Crop_Cultivation!$C:$C,Crop_Cultivation!$B:$B,D3,Crop_Cultivation!$F:$F,"Actual") -> 1 | F3: =SUMIFS(Expenses!$G:$G,Expenses!$I:$I,D3,Expenses!$H:$H,"Approximate") -> 40000 | G3: =SUMIFS(Harvest!$E:$E,Harvest!$C:$C,D3,Harvest!$F:$F,"Approximate") -> 1200 | H3: =SUMIFS(Sales!$F:$F,Sales!$C:$C,D3,Sales!$G:$G,"Approximate") -> 96000 | I3: =H3-F3 -> 56000 | J3: =IFERROR(I3/F3,0) -> 1.4
A4: Total Production (Kg) | B4: =SUM(G2:G4) -> 6590 | D4: Lady's Finger | E4: =SUMIFS(Crop_Cultivation!$C:$C,Crop_Cultivation!$B:$B,D4,Crop_Cultivation!$F:$F,"Actual") -> 1 | F4: =SUMIFS(Expenses!$G:$G,Expenses!$I:$I,D4,Expenses!$H:$H,"Approximate") -> 60500 | G4: =SUMIFS(Harvest!$E:$E,Harvest!$C:$C,D4,Harvest!$F:$F,"Approximate") -> 390 | H4: =SUMIFS(Sales!$F:$F,Sales!$C:$C,D4,Sales!$G:$G,"Approximate") -> 39000 | I4: =H4-F4 -> -21500 | J4: =IFERROR(I4/F4,0) -> -0.3553719
A5: Total Revenue | B5: =SUM(H2:H4) -> 235000
A6: Total Profit | B6: =B5-B3 -> 81300 | D6: Month | E6: Status | F6: Area_Acres | G6: Total_Cost | H6: Production_Kg | I6: Revenue | J6: Profit | K6: ROI_%
A7: Cost Per Acre | B7: =B3/B2 -> 38425 | D7: January | E7: Actual | F7: =SUMIFS(Crop_Cultivation!$C:$C,Crop_Cultivation!$D:$D,D7,Crop_Cultivation!$F:$F,E7) -> 3 | G7: =SUMIFS(Expenses!$G:$G,Expenses!$J:$J,D7,Expenses!$K:$K,E7) -> 113700 | H7: =SUMIFS(Harvest!$E:$E,Harvest!$G:$G,D7,Harvest!$H:$H,E7) -> 5390 | I7: =SUMIFS(Sales!$F:$F,Sales!$H:$H,D7,Sales!$I:$I,E7) -> 139000 | J7: =IF(E7="Planned","",I7-G7) -> 25300 | K7: =IF(E7="Planned","",J7/G7) -> 0.22251539
A8: Yield Per Acre | B8: =B4/B2 -> 1647.5 | D8: February | E8: Actual | F8: =SUMIFS(Crop_Cultivation!$C:$C,Crop_Cultivation!$D:$D,D8,Crop_Cultivation!$F:$F,E8) -> 1 | G8: =SUMIFS(Expenses!$G:$G,Expenses!$J:$J,D8,Expenses!$K:$K,E8) -> 40000 | H8: =SUMIFS(Harvest!$E:$E,Harvest!$G:$G,D8,Harvest!$H:$H,E8) -> 1200 | I8: =SUMIFS(Sales!$F:$F,Sales!$H:$H,D8,Sales!$I:$I,E8) -> 96000 | J8: =IF(E8="Planned","",I8-G8) -> 56000 | K8: =IF(E8="Planned","",J8/G8) -> 1.4
A9: ROI % | B9: =IFERROR(B6/B3,0) -> 0.5289525 | D9: September | E9: Planned | F9: =SUMIFS(Crop_Cultivation!$C:$C,Crop_Cultivation!$D:$D,D9,Crop_Cultivation!$F:$F,E9) -> 4 | G9: =SUMIFS(Expenses!$G:$G,Expenses!$J:$J,D9,Expenses!$K:$K,E9) -> 153700 | H9: =SUMIFS(Harvest!$E:$E,Harvest!$G:$G,D9,Harvest!$H:$H,E9) -> 0 | I9: =SUMIFS(Sales!$F:$F,Sales!$H:$H,D9,Sales!$I:$I,E9) -> 0 | J9: =IF(E9="Planned","",I9-G9) | K9: =IF(E9="Planned","",J9/G9)
A11: Check | B11: Result | D11: Check | E11: Result
A12: Actual cultivated area | B12: =SUMIFS(Crop_Cultivation!C:C,Crop_Cultivation!F:F,"Actual") -> 4 | D12: Total Harvest | E12: =SUM(Harvest!E:E) -> 6590
A13: Expected farm area | B13: 4 | D13: Total Sold | E13: =SUM(Sales!D:D) -> 6590
A14: Area check | B14: =IF(B12=B13,"PASS","CHECK") -> PASS | D14: Difference | E14: =B16-B17 -> 0
D15: Sales reconciliation | E15: =IF(B18=0,"PASS","CHECK") -> PASS

Sheet Dashboard
A1: FARMVISION 2026
A2: Farm Performance & Profitability Dashboard
A3: Dindigul District | 8½ Bus Thottam | 4 Acres | 2026
A4: Total Area | C4: Total Expenses | E4: Total Revenue | G4: Total Profit | I4: Overall ROI
A5: =Summary!B2 -> 4 | C5: =Summary!B3 -> 153700 | E5: =Summary!B5 -> 235000 | G5: =Summary!B6 -> 81300 | I5: =Summary!B9 -> 0.5289525

Sheet Insights
A1: FarmVision 2026 — Key Insights
A2: Insight | B2: Finding
A3: Most Profitable Crop | B3: Cotton generated the highest profit of ₹56,000.
A4: Highest Revenue Crop | B4: Maize generated the highest revenue of ₹100,000.
A5: Highest ROI Crop | B5: Cotton achieved the highest ROI at 140%.
A6: Lowest Performing Crop | B6: Lady's Finger recorded a loss of ₹21,500 and an ROI of −35.54%.
A7: Monthly Performance | B7: February generated ₹56,000 profit from 1 acre, compared with ₹25,300 profit from 3 acres in January.
A8: Key Recommendation | B8: Review Lady's Finger cultivation costs and selling price before expanding its cultivated area. Cotton currently shows the strongest profitability and ROI among the analyzed crops.

Sheet Data_Dictionary
A1: Field_Name | B1: Description | C1: Data_Type | D1: Example
A2: Cultivation_ID | B2: Unique ID for each crop cultivation cycle | C2: Text | D2: C001
A3: Crop | B3: Name of crop cultivated | C3: Text | D3: Maize
A4: Area_Acres | B4: Area used for cultivation | C4: Number | D4: 2
A5: Planting_Month | B5: Month cultivation started | C5: Text | D5: January
A6: Year | B6: Cultivation year | C6: Number | D6: 2026
A7: Cultivation_Status | B7: Actual or planned cultivation | C7: Text | D7: Actual
A8: Expense_ID | B8: Unique ID for each expense | C8: Text | D8: E001
A9: Cultivation_ID | B9: Links expense to cultivation cycle | C9: Text | D9: C002
A10: Category | B10: Main expense group | C10: Text | D10: Fertilizer
A11: Type | B11: Specific expense | C11: Text | D11: Weeding
A12: Amount_Per_Acre | B12: Approximate cost for one acre | C12: Number | D12: 3000
A13: Area | B13: Area to which expense applies | C13: Number | D13: 2
A14: Total | B14: Calculated expense | C14: Number | D14: 6000
A15: Status | B15: Whether the expense is approximate/planned | C15: Text | D15: Approximate
A16: Harvest_ID | B16: Unique harvest record ID | C16: Text | D16: H001
A17: Cultivation_ID | B17: Links harvest to cultivation cycle | C17: Text | D17: C002
A18: Crop | B18: Harvested crop | C18: Text | D18: Maize
A19: Harvest_No | B19: Harvest sequence number | C19: Number | D19: 1
A20: Quantity_Kg | B20: Total harvested quantity | C20: Number | D20: 5000
A21: Data_Status | B21: Quality/status of harvest value | C21: Text | D21: Approximate
A22: Planting_Month | B22: Month cultivation started | C22: Text | D22: January
A23: Cultivation_Status | B23: Actual or planned cultivation | C23: Text | D23: Actual
A24: Sale_ID | B24: Unique sales record ID | C24: Text | D24: S001
A25: Cultivation_ID | B25: Links sale to cultivation cycle | C25: Text | D25: C002
A26: Crop | B26: Crop sold | C26: Text | D26: Maize
A27: Quantity_Kg | B27: Quantity sold | C27: Number | D27: 5000
A28: Selling_Price_Per_Kg | B28: Selling price per kg | C28: Number | D28: 20
A29: Total_Revenue | B29: Quantity × selling price | C29: Number | D29: 100000
A30: Data_Status | B30: Quality/status of sales value | C30: Text | D30: Approximate
